{
	"class" : {
		"on:" : "tb 11/28/2005 17:34",
		"onUrl:" : "tb 11/28/2005 10:35" },
	"instance" : {
		"bruteForceAnalyze" : "tb 12/4/2005 23:01",
		"checkHtmlHeadBody" : "tb 1/15/2006 19:26",
		"content" : "tb 11/28/2005 17:35",
		"content:" : "sebastian.sastre 9/20/2010 11:51",
		"cssErrors" : "tb 1/13/2006 18:42",
		"document" : "sebastian.sastre 10/18/2010 11:56",
		"document:" : "PK 10/18/2010 22:35",
		"dom" : "tb 4/14/2006 21:55",
		"dom:" : "sebastian.sastre 9/20/2010 11:53",
		"errors" : "tb 11/28/2005 10:38",
		"errors:" : "PK 10/18/2010 22:36",
		"htmlErrors" : "pf 7/23/2014 15:48",
		"initialize" : "tb 11/28/2005 10:37",
		"loader" : "tb 1/10/2006 19:34",
		"loader:" : "PK 10/18/2010 22:36",
		"parse" : "tb 1/10/2006 19:48",
		"parseStylesheets" : "tb 1/10/2006 19:50",
		"stylesheets" : "tb 12/30/2005 18:52",
		"url" : "tb 11/28/2005 10:37",
		"url:" : "tb 1/10/2006 15:07",
		"validate" : "tb 1/10/2006 19:47",
		"validateAgainstDTD:" : "tb 1/14/2006 14:04",
		"validateCSSAgainstDTD:" : "tb 1/14/2006 21:39",
		"validateCSSImports" : "tb 1/6/2006 17:31" } }
