{
	"class" : {
		 },
	"instance" : {
		"setUp" : "fm 7/29/2015 19:03",
		"tearDown" : "MR 7/18/2016 19:23",
		"test00Open" : "MR 7/18/2016 19:25",
		"test01jumpToRelativeUrl" : "MR 5/24/2016 12:58",
		"test02submitForm" : "wg 7/16/2015 11:41",
		"test03DocumentWithoutTitleTagShouldntRaiseErrors" : "wg 7/16/2015 11:41",
		"test04testRealWorldCookies" : "MR 5/29/2016 16:27",
		"test05isUrl" : "fm 7/29/2015 18:50",
		"test06isInternBrowser" : "MR 7/3/2016 16:34",
		"test07intializeMIMEDatabase" : "fm 7/29/2015 19:00",
		"test08addBookmark" : "LL 6/13/2016 15:37",
		"test09newTab" : "ak 6/16/2016 10:12",
		"test10scrolling" : "MW 6/15/2016 11:41",
		"test11httpStatus400" : "MR 6/22/2016 18:49",
		"test12httpStatus401" : "MR 6/22/2016 18:50",
		"test13httpStatus402" : "MR 6/22/2016 18:50",
		"test14httpStatus403" : "MR 6/22/2016 18:50",
		"test15httpStatus404" : "MR 6/22/2016 18:50",
		"test16httpStatus405" : "MR 6/22/2016 18:51",
		"test17httpStatus406" : "MR 6/22/2016 18:52",
		"test18httpStatus407" : "MR 6/22/2016 18:52",
		"test19httpStatus408" : "MR 6/22/2016 18:52",
		"test20httpStatus409" : "MR 6/22/2016 18:53",
		"test21httpStatus410" : "MR 6/22/2016 18:53",
		"test22httpStatus411" : "MR 6/22/2016 18:54",
		"test23httpStatus412" : "MR 6/22/2016 18:54",
		"test24httpStatus413" : "MR 6/22/2016 18:54",
		"test25httpStatus414" : "MR 6/22/2016 18:54",
		"test26httpStatus415" : "MR 6/22/2016 18:55",
		"test27httpStatus416" : "MR 6/22/2016 18:55",
		"test28httpStatus417" : "MR 6/22/2016 18:56",
		"test29httpStatus418" : "MR 6/22/2016 19:18",
		"test30httpStatus420" : "MR 6/22/2016 18:56",
		"test31httpStatus421" : "MR 6/22/2016 18:58",
		"test32httpStatus422" : "MR 6/22/2016 18:58",
		"test33httpStatus423" : "MR 6/22/2016 18:58",
		"test34httpStatus424" : "MR 6/22/2016 18:59",
		"test35httpStatus425" : "MR 6/22/2016 18:59",
		"test36httpStatus426" : "MR 6/22/2016 18:59",
		"test38httpStatus428" : "MR 6/22/2016 19:00",
		"test39httpStatus429" : "MR 6/22/2016 19:00",
		"test40httpStatus431" : "MR 6/22/2016 19:01",
		"test41httpStatus451" : "MR 6/22/2016 19:01",
		"test42httpStatus500" : "MR 6/22/2016 19:09",
		"test43httpStatus501" : "MR 6/22/2016 19:10",
		"test44httpStatus502" : "MR 6/22/2016 19:10",
		"test45httpStatus503" : "MR 6/22/2016 19:10",
		"test46httpStatus504" : "MR 6/22/2016 19:10",
		"test47httpStatus505" : "MR 6/22/2016 19:11",
		"test48httpStatus506" : "MR 6/22/2016 19:11",
		"test49httpStatus507" : "MR 6/22/2016 19:11",
		"test50httpStatus508" : "MR 6/22/2016 19:12",
		"test51httpStatus509" : "MR 6/22/2016 19:12",
		"test52httpStatus510" : "MR 6/22/2016 19:12",
		"test53httpStatus511" : "MR 6/22/2016 19:13",
		"test54StopButtonBehaviour" : "MR 7/3/2016 17:45",
		"test55ReloadButtonBehaviour" : "MR 7/3/2016 17:43",
		"test56furtherOptionsButtonsBehaviour" : "MR 7/8/2016 21:09",
		"test57furtherOptionsPanelPosition" : "MR 7/18/2016 17:31",
		"test58furtherOptionsButtons" : "MR 7/18/2016 21:54" } }
